[
  {
    "goodChoises": [
      {
        "choise": " Настройка защищённого \n документооборота (DLP)",
        "answer": " DLP (Data Loss Prevention) — это технология, \n которая позволяет организациям защищать \n конфиденциальную информацию от кражи \n и несанкционированного доступа. \n Хорошая работа"
      }
    ],
    "badChoises": [],
    "deadChoises": [
      {
        "choise": " Нет, нельзя ",
        "answer": " Сотруднику не понравился \n ваш ответ и он уволился"
      }
    ]
  }
]
